fh_fablib/__init__.py
fh_fablib/extract_js_gettext_strings.py
fh_fablib/dotfiles/.editorconfig
fh_fablib/dotfiles/.pre-commit-config.yaml
fh_fablib/dotfiles/biome.json
fh_fablib/dotfiles/pyproject.toml
fh_fablib/dotfiles/rspack.library.js
fh_fablib/dotfiles/webpack.library.js
fh_fablib-1.0.20250710.dist-info/METADATA
fh_fablib-1.0.20250710.dist-info/WHEEL
fh_fablib-1.0.20250710.dist-info/entry_points.txt
fh_fablib-1.0.20250710.dist-info/licenses/LICENSE
fh_fablib-1.0.20250710.dist-info/RECORD
