Metadata-Version: 2.4
Name: fh-fablib
Version: 1.0.20250710
Summary: fh-fablib
Project-URL: Homepage, https://github.com/feinheit/fh-fablib/
Author-email: Matthias Kestenholz <mk@feinheit.ch>
License: BSD-3-Clause
License-File: LICENSE
Classifier: License :: OSI Approved :: BSD License
Requires-Python: >=3.9
Requires-Dist: fabric>=3
Requires-Dist: speckenv>=6.2
